tradingkit/cli/__init__.py
tradingkit/cli/cli.py
tradingkit/cli/optimizer.py
tradingkit/cli/runner.py
tradingkit/config/__init__.py
tradingkit/config/config.json
tradingkit/data/__init__.py
tradingkit/data/adapter/__init__.py
tradingkit/data/adapter/adapter.py
tradingkit/data/adapter/bitmex_normalizer.py
tradingkit/data/adapter/outlier_trade_filter.py
tradingkit/data/feed/__init__.py
tradingkit/data/feed/aggregator_feeder.py
tradingkit/data/feed/backtest_feeder.py
tradingkit/data/feed/bitmex_feeder.py
tradingkit/data/feed/feeder.py
tradingkit/data/feed/funding_backtest_feeder.py
tradingkit/data/feed/kraken_feeder.py
tradingkit/data/feed/list_feeder.py
tradingkit/data/feed/private_kraken_feeder.py
tradingkit/data/feed/public_kraken_feeder.py
tradingkit/data/feed/websocket_feeder.py
tradingkit/data/fetch/__init__.py
tradingkit/data/fetch/ccxt_fetcher.py
tradingkit/data/fetch/fetcher.py
tradingkit/display/__init__.py
tradingkit/display/none_plotter.py
tradingkit/display/plotly_plotter.py
tradingkit/display/plotter.py
tradingkit/display/highstock/__init__.py
tradingkit/display/highstock/highstock_plotter.py
tradingkit/display/highstock/lib/index.html
tradingkit/display/highstock/lib/live.html
tradingkit/display/highstock/lib/live_balance.html
tradingkit/display/highstock/server/plot_server.py
tradingkit/exchange/__init__.py
tradingkit/exchange/bitmex_backtest.py
tradingkit/exchange/bridge_exchange.py
tradingkit/exchange/testex.py
tradingkit/pubsub/__init__.py
tradingkit/pubsub/core/__init__.py
tradingkit/pubsub/core/event.py
tradingkit/pubsub/core/publisher.py
tradingkit/pubsub/core/subscriber.py
tradingkit/pubsub/event/__init__.py
tradingkit/pubsub/event/book.py
tradingkit/pubsub/event/candle.py
tradingkit/pubsub/event/funding.py
tradingkit/pubsub/event/liquidation.py
tradingkit/pubsub/event/open_order.py
tradingkit/pubsub/event/order.py
tradingkit/pubsub/event/plot.py
tradingkit/pubsub/event/position.py
tradingkit/pubsub/event/trade.py
tradingkit-1.11.8.dist-info/LICENSE
tradingkit-1.11.8.dist-info/METADATA
tradingkit-1.11.8.dist-info/WHEEL
tradingkit-1.11.8.dist-info/entry_points.txt
tradingkit-1.11.8.dist-info/top_level.txt
tradingkit-1.11.8.dist-info/RECORD
