Metadata-Version: 2.1
Name: tradingkit
Version: 1.11.8
Summary: Trading and backtesting framework for Python
Home-page: https://github.com/logictraders/tradingkit
Author: QBit Artifacts, SL
Author-email: lluis@logictraders.com
License: MIT
Classifier: Development Status :: 3 - Alpha
Classifier: Programming Language :: Python
Classifier: Programming Language :: Python :: 3
Classifier: Programming Language :: Python :: 3.7
Classifier: Programming Language :: Python :: 3.8
Classifier: Programming Language :: Python :: 3.9
Classifier: Environment :: Console
Classifier: License :: OSI Approved :: MIT License
Classifier: Operating System :: OS Independent
Classifier: Intended Audience :: Developers
Classifier: Topic :: Office/Business
Classifier: Topic :: Software Development
Classifier: Topic :: Software Development :: Build Tools
Classifier: Topic :: Software Development :: Libraries
Classifier: Topic :: Software Development :: Libraries :: Python Modules
Classifier: Topic :: Software Development :: Libraries :: Application Frameworks
License-File: LICENSE
Requires-Dist: ccxt (==3.1.10)
Requires-Dist: docopt (~=0.6.2)
Requires-Dist: python-dateutil (~=2.8.1)
Requires-Dist: plotly (==5.12.0)
Requires-Dist: pandas (==1.5.2)
Requires-Dist: setuptools (==66.0.0)
Requires-Dist: numpy (==1.24.1)
Requires-Dist: requests (==2.28.2)
Requires-Dist: chardet (==3.0.4)
Requires-Dist: python-dotenv (==0.21.0)
Requires-Dist: websocket-client (==1.4.2)
Requires-Dist: coverage (==7.0.5)
Requires-Dist: websockets (==10.4)
